odoo/addons/sale_report_delivered_deposit/README.rst
odoo/addons/sale_report_delivered_deposit/__init__.py
odoo/addons/sale_report_delivered_deposit/__manifest__.py
odoo/addons/sale_report_delivered_deposit/i18n/it.po
odoo/addons/sale_report_delivered_deposit/i18n/sale_report_delivered_deposit.pot
odoo/addons/sale_report_delivered_deposit/readme/CONTEXT.md
odoo/addons/sale_report_delivered_deposit/readme/CONTRIBUTORS.md
odoo/addons/sale_report_delivered_deposit/readme/CREDITS.md
odoo/addons/sale_report_delivered_deposit/readme/DESCRIPTION.md
odoo/addons/sale_report_delivered_deposit/readme/USAGE.md
odoo/addons/sale_report_delivered_deposit/report/__init__.py
odoo/addons/sale_report_delivered_deposit/report/sale_report.py
odoo/addons/sale_report_delivered_deposit/static/description/icon.png
odoo/addons/sale_report_delivered_deposit/static/description/index.html
odoo/addons/sale_report_delivered_deposit/tests/__init__.py
odoo/addons/sale_report_delivered_deposit/tests/test_sale_report_delivered_deposit.py
odoo_addon_sale_report_delivered_deposit-16.0.2.0.0.2.dist-info/METADATA
odoo_addon_sale_report_delivered_deposit-16.0.2.0.0.2.dist-info/WHEEL
odoo_addon_sale_report_delivered_deposit-16.0.2.0.0.2.dist-info/top_level.txt
odoo_addon_sale_report_delivered_deposit-16.0.2.0.0.2.dist-info/RECORD
