Metadata-Version: 2.1
Name: odoo-addon-sale_report_delivered_deposit
Version: 16.0.2.0.0.2
Summary: Allow to view Customer Deposits on Sale Report Delivered
Home-page: https://github.com/OCA/sale-reporting
Author: Moduon, Odoo Community Association (OCA)
Author-email: support@odoo-community.org
License: AGPL-3
Classifier: Programming Language :: Python
Classifier: Framework :: Odoo
Classifier: Framework :: Odoo :: 16.0
Classifier: License :: OSI Approved :: GNU Affero General Public License v3
Classifier: Development Status :: 3 - Alpha
Requires-Python: >=3.10
Requires-Dist: odoo-addon-sale-report-delivered<16.1dev,>=16.0dev
Requires-Dist: odoo-addon-stock-customer-deposit<16.1dev,>=16.0dev
Requires-Dist: odoo<16.1dev,>=16.0a
